preset/__init__.py
preset/pony/__init__.py
preset-0.1.1.dist-info/METADATA
preset-0.1.1.dist-info/RECORD
preset-0.1.1.dist-info/WHEEL
preset-0.1.1.dist-info/top_level.txt
